[
    {
        "name": "Physical Chess AI",
        "association": "Undergraduate Senior Project",
        "description": "Designed a chessboard that automatically detects a players move, tracks the board's state, and communicates an AI's response.",
        "image": "/chessboard.png"
    },
    {
        "name": "Scheduling Service",
        "association": "Capstone Project with Lockheed Martin",
        "description": "Implemented a real-time scheduling service using Lockheed Martin’s SmartSat™ SDK.",
        "image": "/SCRiPT.png"
    },
    {
        "name": "Some Networking Project",
        "association": "Intro to Networks, or Networking Security",
        "description": "Did a thing or something.",
        "image": "/SCRiPT.png"
    }
]